tabnetviz/__init__.py
tabnetviz/__main__.py
tabnetviz/colorbarsvg.py
tabnetviz/configtemplate.py
tabnetviz/gvattrs.py
tabnetviz/kwcheck.py
tabnetviz/netanalyzer.py
tabnetviz-1.3.dist-info/LICENSE.txt
tabnetviz-1.3.dist-info/METADATA
tabnetviz-1.3.dist-info/WHEEL
tabnetviz-1.3.dist-info/entry_points.txt
tabnetviz-1.3.dist-info/top_level.txt
tabnetviz-1.3.dist-info/RECORD
